mensa.py
mensa_kl_cli-0.1.dist-info/LICENSE
mensa_kl_cli-0.1.dist-info/METADATA
mensa_kl_cli-0.1.dist-info/WHEEL
mensa_kl_cli-0.1.dist-info/entry_points.txt
mensa_kl_cli-0.1.dist-info/top_level.txt
mensa_kl_cli-0.1.dist-info/RECORD
